odoo/addons/purchase_invoice_method/README.rst
odoo/addons/purchase_invoice_method/__init__.py
odoo/addons/purchase_invoice_method/__manifest__.py
odoo/addons/purchase_invoice_method/i18n/es.po
odoo/addons/purchase_invoice_method/i18n/es_MX.po
odoo/addons/purchase_invoice_method/i18n/it.po
odoo/addons/purchase_invoice_method/i18n/pt_BR.po
odoo/addons/purchase_invoice_method/i18n/purchase_invoice_method.pot
odoo/addons/purchase_invoice_method/models/__init__.py
odoo/addons/purchase_invoice_method/models/purchase_order.py
odoo/addons/purchase_invoice_method/readme/CONTRIBUTORS.md
odoo/addons/purchase_invoice_method/readme/DESCRIPTION.md
odoo/addons/purchase_invoice_method/readme/USAGE.md
odoo/addons/purchase_invoice_method/static/description/icon.png
odoo/addons/purchase_invoice_method/static/description/index.html
odoo/addons/purchase_invoice_method/tests/__init__.py
odoo/addons/purchase_invoice_method/tests/test_purchase_invoice_method.py
odoo/addons/purchase_invoice_method/views/purchase_order.xml
odoo_addon_purchase_invoice_method-18.0.1.0.0.3.dist-info/METADATA
odoo_addon_purchase_invoice_method-18.0.1.0.0.3.dist-info/WHEEL
odoo_addon_purchase_invoice_method-18.0.1.0.0.3.dist-info/top_level.txt
odoo_addon_purchase_invoice_method-18.0.1.0.0.3.dist-info/RECORD
